BLACKEYED/__init__.py
BLACKEYED/main.py
Blackeyed-0.0.1.dist-info/License
Blackeyed-0.0.1.dist-info/METADATA
Blackeyed-0.0.1.dist-info/WHEEL
Blackeyed-0.0.1.dist-info/top_level.txt
Blackeyed-0.0.1.dist-info/RECORD
