Metadata-Version: 2.1
Name: Blackeyed
Version: 0.0.1
Summary: Best TV series package
Home-page: https://gitlab.com/Chernookiy19
Author: Evgeniy Chernookiy
Author-email: ChernookiyEvgeniy@gmil.com
License: UNKNOWN
Platform: UNKNOWN
Classifier: Programming Language :: Python :: 3.8
Classifier: License :: OSI Approved :: MIT License
Requires-Python: >=3.8
License-File: License
